{
  "IsEncrypted": false,
  "Values": {
    "AzureWebJobsStorage": "UseDevelopmentStorage=true",
    "FUNCTIONS_WORKER_RUNTIME": "dotnet",
    "ServiceBusConnectionString": "<ConnectionString>",
    "SearchServiceEndPoint": "<Endpoint>",
    "SearchServiceAdminApiKey": "<Key>",
    "SearchServiceIndexName": "<IndexName>",
    "SignalrServiceConnectionString": "<ConnectionString>",
    "RedisCacheConnectionString": "<ConnectionString>"
  },
  "Host": {
    "LocalHttpPort": 7203,
    "CORS": "*",
    "CORSCredentials": false
  }
}
